ansible_gen/__init__.py
ansible_gen/ansible_gen.py
ansible_gen/adapter/__init__.py
ansible_gen/adapter/gen_examples.py
ansible_gen/adapter/get_argument_spec_documentation.py
ansible_gen/adapter/get_imp_cls_def.py
ansible_gen/adapter/get_rpc_head_tail.py
ansible_gen/adapter/utils/__init__.py
ansible_gen/adapter/utils/base_util.py
ansible_gen/adapter/utils/xml_parse/__init__.py
ansible_gen/adapter/utils/xml_parse/xml_parser.py
ansible_gen/adapter/utils/xml_parse/xml_parser_get_xmlns.py
ansible_gen/adapter/utils/yang_parse/__init__.py
ansible_gen/adapter/utils/yang_parse/constant.py
ansible_gen/adapter/utils/yang_parse/interfaces.py
ansible_gen/adapter/utils/yang_parse/pyang_util.py
ansible_gen/adapter/utils/yang_parse/pyang_wrapper.py
ansible_gen/adapter/utils/yang_parse/utils.py
ansible_gen/adapter/utils/yang_parse/yang_parser.py
ansible_gen/generator/__init__.py
ansible_gen/generator/ansible_auto_scripts.py
ansible_gen/generator/checkparams.py
ansible_gen/generator/move_file.py
ansible_gen/generator/ne_base.py
ansible_gen/generator/var.py
ansible_gen/generator/xml_build_with_xmlns.py
ansible_gen/generator/templates/module.html
ansible_gen-1.0.0.dist-info/LICENSE
ansible_gen-1.0.0.dist-info/METADATA
ansible_gen-1.0.0.dist-info/WHEEL
ansible_gen-1.0.0.dist-info/entry_points.txt
ansible_gen-1.0.0.dist-info/top_level.txt
ansible_gen-1.0.0.dist-info/RECORD
